flexdata/__init__.py
flexdata/correct.py
flexdata/data.py
flexdata/display.py
flexdata/geometry.py
flexdata-1.0.1.dist-info/LICENSE.md
flexdata-1.0.1.dist-info/METADATA
flexdata-1.0.1.dist-info/WHEEL
flexdata-1.0.1.dist-info/top_level.txt
flexdata-1.0.1.dist-info/RECORD
